common_image_tools/__init__.py
common_image_tools/conversion.py
common_image_tools/operation.py
common_image_tools/tool.py
common_image_tools/verification.py
common_image_tools/video_source.py
common_image_tools/visualization.py
common_image_tools-1.0.1.dist-info/METADATA
common_image_tools-1.0.1.dist-info/WHEEL
common_image_tools-1.0.1.dist-info/RECORD
