Metadata-Version: 2.4
Name: common_image_tools
Version: 1.0.1
Author-email: Federico Lanzani <hello@federicolanzani.com>
Requires-Python: >=3.10
Requires-Dist: color-transfer>=0.1
Requires-Dist: loguru>=0.7.0
Requires-Dist: pillow>=10.2.0
